Metadata-Version: 1.0
Name: lluser
Version: 1.33
Summary: 上次登录的用户，last login user
Home-page: http://dadadakeai.com/lluser/index.html
Author: oyy
Author-email: oyy284688@gmail.com
License: GUN
Platform: UNKNOWN
